xloft/__init__.py
xloft/errors.py
xloft/itis.py
xloft/py.typed
xloft/converters/__init__.py
xloft/converters/human_size.py
xloft/converters/roman.py
xloft/types/__init__.py
xloft/types/alias_dict.py
xloft/types/named_tuple.py
xloft-0.10.10.dist-info/METADATA
xloft-0.10.10.dist-info/WHEEL
xloft-0.10.10.dist-info/licenses/LICENSE
xloft-0.10.10.dist-info/RECORD
