Metadata-Version: 2.4
Name: xloft
Version: 0.10.10
Summary: (XLOFT) X-Library of tools
Project-URL: Homepage, https://kebasyaty.github.io/xloft/
Project-URL: Repository, https://github.com/kebasyaty/xloft
Project-URL: Source, https://github.com/kebasyaty/xloft
Project-URL: Bug Tracker, https://github.com/kebasyaty/xloft/issues
Project-URL: Changelog, https://github.com/kebasyaty/xloft/blob/v0/CHANGELOG.md
Author-email: kebasyaty <kebasyaty@gmail.com>
License-Expression: MIT
License-File: LICENSE
Keywords: aliasdict,collection,namedtuple,tools,xloft
Classifier: Development Status :: 5 - Production/Stable
Classifier: Intended Audience :: Developers
Classifier: License :: OSI Approved :: MIT License
Classifier: Operating System :: MacOS :: MacOS X
Classifier: Operating System :: Microsoft :: Windows
Classifier: Operating System :: POSIX
Classifier: Operating System :: POSIX :: Linux
Classifier: Programming Language :: Python :: 3
Classifier: Programming Language :: Python :: 3 :: Only
Classifier: Programming Language :: Python :: 3.12
Classifier: Programming Language :: Python :: 3.13
Classifier: Programming Language :: Python :: 3.14
Classifier: Programming Language :: Python :: Implementation :: CPython
Classifier: Topic :: Software Development :: Libraries
Classifier: Topic :: Software Development :: Libraries :: Python Modules
Classifier: Topic :: Utilities
Classifier: Typing :: Typed
Requires-Python: <4.0,>=3.12
